zipndel/__init__.py
zipndel/zipndel.py
zipndel-0.1.0.dist-info/WHEEL
zipndel-0.1.0.dist-info/METADATA
zipndel-0.1.0.dist-info/RECORD
